azure/mgmt/machinelearningservices/__init__.py
azure/mgmt/machinelearningservices/_azure_machine_learning_workspaces.py
azure/mgmt/machinelearningservices/_configuration.py
azure/mgmt/machinelearningservices/_version.py
azure/mgmt/machinelearningservices/aio/__init__.py
azure/mgmt/machinelearningservices/aio/_azure_machine_learning_workspaces.py
azure/mgmt/machinelearningservices/aio/_configuration.py
azure/mgmt/machinelearningservices/aio/operations/__init__.py
azure/mgmt/machinelearningservices/aio/operations/_azure_machine_learning_workspaces_operations.py
azure/mgmt/machinelearningservices/aio/operations/_machine_learning_compute_operations.py
azure/mgmt/machinelearningservices/aio/operations/_notebooks_operations.py
azure/mgmt/machinelearningservices/aio/operations/_operations.py
azure/mgmt/machinelearningservices/aio/operations/_private_endpoint_connections_operations.py
azure/mgmt/machinelearningservices/aio/operations/_private_link_resources_operations.py
azure/mgmt/machinelearningservices/aio/operations/_quotas_operations.py
azure/mgmt/machinelearningservices/aio/operations/_usages_operations.py
azure/mgmt/machinelearningservices/aio/operations/_virtual_machine_sizes_operations.py
azure/mgmt/machinelearningservices/aio/operations/_workspace_connections_operations.py
azure/mgmt/machinelearningservices/aio/operations/_workspace_features_operations.py
azure/mgmt/machinelearningservices/aio/operations/_workspaces_operations.py
azure/mgmt/machinelearningservices/models/__init__.py
azure/mgmt/machinelearningservices/models/_azure_machine_learning_workspaces_enums.py
azure/mgmt/machinelearningservices/models/_models.py
azure/mgmt/machinelearningservices/models/_models_py3.py
azure/mgmt/machinelearningservices/operations/__init__.py
azure/mgmt/machinelearningservices/operations/_azure_machine_learning_workspaces_operations.py
azure/mgmt/machinelearningservices/operations/_machine_learning_compute_operations.py
azure_mgmt_machinelearningservices-1.0.0.dist-info/METADATA
azure_mgmt_machinelearningservices-1.0.0.dist-info/WHEEL
azure_mgmt_machinelearningservices-1.0.0.dist-info/top_level.txt
azure_mgmt_machinelearningservices-1.0.0.dist-info/RECORD
